ChanzhongshuochanShizhanLilun/README.md
ChanzhongshuochanShizhanLilun/__init__.py
ChanzhongshuochanShizhanLilun/__main__.py
ChanzhongshuochanShizhanLilun/file.epub
ChanzhongshuochanShizhanLilun/index.html
ChanzhongshuochanShizhanLilun/css/__init__.py
ChanzhongshuochanShizhanLilun/css/annotations.css
ChanzhongshuochanShizhanLilun/css/main.css
ChanzhongshuochanShizhanLilun/css/normalize.css
ChanzhongshuochanShizhanLilun/css/popup.css
ChanzhongshuochanShizhanLilun/font/__init__.py
ChanzhongshuochanShizhanLilun/font/fontello.eot
ChanzhongshuochanShizhanLilun/font/fontello.svg
ChanzhongshuochanShizhanLilun/font/fontello.ttf
ChanzhongshuochanShizhanLilun/font/fontello.woff
ChanzhongshuochanShizhanLilun/img/__init__.py
ChanzhongshuochanShizhanLilun/img/annotator-glyph-sprite.png
ChanzhongshuochanShizhanLilun/img/annotator-icon-sprite.png
ChanzhongshuochanShizhanLilun/img/apple-touch-icon.png
ChanzhongshuochanShizhanLilun/img/cancelfullscreen.png
ChanzhongshuochanShizhanLilun/img/close.png
ChanzhongshuochanShizhanLilun/img/fullscreen.png
ChanzhongshuochanShizhanLilun/img/loader.gif
ChanzhongshuochanShizhanLilun/img/menu-icon.png
ChanzhongshuochanShizhanLilun/img/save.png
ChanzhongshuochanShizhanLilun/img/saved.png
ChanzhongshuochanShizhanLilun/img/settings-s.png
ChanzhongshuochanShizhanLilun/img/settings.png
ChanzhongshuochanShizhanLilun/img/star.png
ChanzhongshuochanShizhanLilun/js/__init__.py
ChanzhongshuochanShizhanLilun/js/epub.js
ChanzhongshuochanShizhanLilun/js/epub.min.js
ChanzhongshuochanShizhanLilun/js/epub.min.map
ChanzhongshuochanShizhanLilun/js/hooks.min.js
ChanzhongshuochanShizhanLilun/js/hooks.min.map
ChanzhongshuochanShizhanLilun/js/reader.js
ChanzhongshuochanShizhanLilun/js/reader.js.map
ChanzhongshuochanShizhanLilun/js/reader.min.js
ChanzhongshuochanShizhanLilun/js/reader.min.map
ChanzhongshuochanShizhanLilun/js/hooks/__init__.py
ChanzhongshuochanShizhanLilun/js/hooks/extensions/__init__.py
ChanzhongshuochanShizhanLilun/js/hooks/extensions/highlight.js
chanzhongshuochan_shizhan_lilun-2022.10.15.0.dist-info/METADATA
chanzhongshuochan_shizhan_lilun-2022.10.15.0.dist-info/WHEEL
chanzhongshuochan_shizhan_lilun-2022.10.15.0.dist-info/entry_points.txt
chanzhongshuochan_shizhan_lilun-2022.10.15.0.dist-info/top_level.txt
chanzhongshuochan_shizhan_lilun-2022.10.15.0.dist-info/RECORD
